calculator/__init__.py
calculator/calculator.py
calculatores-1.1.0.dist-info/LICENSE
calculatores-1.1.0.dist-info/METADATA
calculatores-1.1.0.dist-info/WHEEL
calculatores-1.1.0.dist-info/top_level.txt
calculatores-1.1.0.dist-info/RECORD
